{"get":"injuries","parameters":{"fixture":"1387873"},"errors":[],"results":11,"paging":{"current":1,"total":1},"response":[{"player":{"id":543470,"name":"P. Cabral","photo":"https:\/\/media.api-sports.io\/football\/players\/543470.png","type":"Missing Fixture","reason":"Muscle Injury"},"team":{"id":91,"name":"Monaco","logo":"https:\/\/media.api-sports.io\/football\/teams\/91.png"},"fixture":{"id":1387873,"timezone":"UTC","date":"2026-01-31T20:05:00+00:00","timestamp":1769889900},"league":{"id":61,"season":2025,"name":"Ligue 1","country":"France","logo":"https:\/\/media.api-sports.io\/football\/leagues\/61.png","flag":"https:\/\/media.api-sports.io\/flags\/fr.svg"}},{"player":{"id":175,"name":"E. Dier","photo":"https:\/\/media.api-sports.io\/football\/players\/175.png","type":"Missing Fixture","reason":"Injury"},"team":{"id":91,"name":"Monaco","logo":"https:\/\/media.api-sports.io\/football\/teams\/91.png"},"fixture":{"id":1387873,"timezone":"UTC","date":"2026-01-31T20:05:00+00:00","timestamp":1769889900},"league":{"id":61,"season":2025,"name":"Ligue 1","country":"France","logo":"https:\/\/media.api-sports.io\/football\/leagues\/61.png","flag":"https:\/\/media.api-sports.io\/flags\/fr.svg"}},{"player":{"id":8694,"name":"W. Faes","photo":"https:\/\/media.api-sports.io\/football\/players\/8694.png","type":"Missing Fixture","reason":"Injury"},"team":{"id":91,"name":"Monaco","logo":"https:\/\/media.api-sports.io\/football\/teams\/91.png"},"fixture":{"id":1387873,"timezone":"UTC","date":"2026-01-31T20:05:00+00:00","timestamp":1769889900},"league":{"id":61,"season":2025,"name":"Ligue 1","country":"France","logo":"https:\/\/media.api-sports.io\/football\/leagues\/61.png","flag":"https:\/\/media.api-sports.io\/flags\/fr.svg"}},{"player":{"id":963,"name":"L. Hradecky","photo":"https:\/\/media.api-sports.io\/football\/players\/963.png","type":"Missing Fixture","reason":"Knee Injury"},"team":{"id":91,"name":"Monaco","logo":"https:\/\/media.api-sports.io\/football\/teams\/91.png"},"fixture":{"id":1387873,"timezone":"UTC","date":"2026-01-31T20:05:00+00:00","timestamp":1769889900},"league":{"id":61,"season":2025,"name":"Ligue 1","country":"France","logo":"https:\/\/media.api-sports.io\/football\/leagues\/61.png","flag":"https:\/\/media.api-sports.io\/flags\/fr.svg"}},{"player":{"id":1101,"name":"T. Minamino","photo":"https:\/\/media.api-sports.io\/football\/players\/1101.png","type":"Missing Fixture","reason":"Knee Injury"},"team":{"id":91,"name":"Monaco","logo":"https:\/\/media.api-sports.io\/football\/teams\/91.png"},"fixture":{"id":1387873,"timezone":"UTC","date":"2026-01-31T20:05:00+00:00","timestamp":1769889900},"league":{"id":61,"season":2025,"name":"Ligue 1","country":"France","logo":"https:\/\/media.api-sports.io\/football\/leagues\/61.png","flag":"https:\/\/media.api-sports.io\/flags\/fr.svg"}},{"player":{"id":904,"name":"P. Pogba","photo":"https:\/\/media.api-sports.io\/football\/players\/904.png","type":"Missing Fixture","reason":"Calf Injury"},"team":{"id":91,"name":"Monaco","logo":"https:\/\/media.api-sports.io\/football\/teams\/91.png"},"fixture":{"id":1387873,"timezone":"UTC","date":"2026-01-31T20:05:00+00:00","timestamp":1769889900},"league":{"id":61,"season":2025,"name":"Ligue 1","country":"France","logo":"https:\/\/media.api-sports.io\/football\/leagues\/61.png","flag":"https:\/\/media.api-sports.io\/flags\/fr.svg"}},{"player":{"id":47480,"name":"M. Salisu","photo":"https:\/\/media.api-sports.io\/football\/players\/47480.png","type":"Missing Fixture","reason":"Knee Injury"},"team":{"id":91,"name":"Monaco","logo":"https:\/\/media.api-sports.io\/football\/teams\/91.png"},"fixture":{"id":1387873,"timezone":"UTC","date":"2026-01-31T20:05:00+00:00","timestamp":1769889900},"league":{"id":61,"season":2025,"name":"Ligue 1","country":"France","logo":"https:\/\/media.api-sports.io\/football\/leagues\/61.png","flag":"https:\/\/media.api-sports.io\/flags\/fr.svg"}},{"player":{"id":371916,"name":"C. Mawissa","photo":"https:\/\/media.api-sports.io\/football\/players\/371916.png","type":"Questionable","reason":"Injury"},"team":{"id":91,"name":"Monaco","logo":"https:\/\/media.api-sports.io\/football\/teams\/91.png"},"fixture":{"id":1387873,"timezone":"UTC","date":"2026-01-31T20:05:00+00:00","timestamp":1769889900},"league":{"id":61,"season":2025,"name":"Ligue 1","country":"France","logo":"https:\/\/media.api-sports.io\/football\/leagues\/61.png","flag":"https:\/\/media.api-sports.io\/flags\/fr.svg"}},{"player":{"id":30807,"name":"S. Fofana","photo":"https:\/\/media.api-sports.io\/football\/players\/30807.png","type":"Missing Fixture","reason":"Calf Injury"},"team":{"id":94,"name":"Rennes","logo":"https:\/\/media.api-sports.io\/football\/teams\/94.png"},"fixture":{"id":1387873,"timezone":"UTC","date":"2026-01-31T20:05:00+00:00","timestamp":1769889900},"league":{"id":61,"season":2025,"name":"Ligue 1","country":"France","logo":"https:\/\/media.api-sports.io\/football\/leagues\/61.png","flag":"https:\/\/media.api-sports.io\/flags\/fr.svg"}},{"player":{"id":449662,"name":"M. Meite","photo":"https:\/\/media.api-sports.io\/football\/players\/449662.png","type":"Missing Fixture","reason":"Inactive"},"team":{"id":94,"name":"Rennes","logo":"https:\/\/media.api-sports.io\/football\/teams\/94.png"},"fixture":{"id":1387873,"timezone":"UTC","date":"2026-01-31T20:05:00+00:00","timestamp":1769889900},"league":{"id":61,"season":2025,"name":"Ligue 1","country":"France","logo":"https:\/\/media.api-sports.io\/football\/leagues\/61.png","flag":"https:\/\/media.api-sports.io\/flags\/fr.svg"}},{"player":{"id":21102,"name":"V. Rongier","photo":"https:\/\/media.api-sports.io\/football\/players\/21102.png","type":"Missing Fixture","reason":"Calf Injury"},"team":{"id":94,"name":"Rennes","logo":"https:\/\/media.api-sports.io\/football\/teams\/94.png"},"fixture":{"id":1387873,"timezone":"UTC","date":"2026-01-31T20:05:00+00:00","timestamp":1769889900},"league":{"id":61,"season":2025,"name":"Ligue 1","country":"France","logo":"https:\/\/media.api-sports.io\/football\/leagues\/61.png","flag":"https:\/\/media.api-sports.io\/flags\/fr.svg"}}]}