{"get":"injuries","parameters":{"fixture":"1391027"},"errors":[],"results":8,"paging":{"current":1,"total":1},"response":[{"player":{"id":183848,"name":"J. Agirrezabala","photo":"https:\/\/media.api-sports.io\/football\/players\/183848.png","type":"Missing Fixture","reason":"Muscle Injury"},"team":{"id":532,"name":"Valencia","logo":"https:\/\/media.api-sports.io\/football\/teams\/532.png"},"fixture":{"id":1391027,"timezone":"UTC","date":"2026-01-24T15:15:00+00:00","timestamp":1769267700},"league":{"id":140,"season":2025,"name":"La Liga","country":"Spain","logo":"https:\/\/media.api-sports.io\/football\/leagues\/140.png","flag":"https:\/\/media.api-sports.io\/flags\/es.svg"}},{"player":{"id":1482,"name":"T. Correia","photo":"https:\/\/media.api-sports.io\/football\/players\/1482.png","type":"Missing Fixture","reason":"Injury"},"team":{"id":532,"name":"Valencia","logo":"https:\/\/media.api-sports.io\/football\/teams\/532.png"},"fixture":{"id":1391027,"timezone":"UTC","date":"2026-01-24T15:15:00+00:00","timestamp":1769267700},"league":{"id":140,"season":2025,"name":"La Liga","country":"Spain","logo":"https:\/\/media.api-sports.io\/football\/leagues\/140.png","flag":"https:\/\/media.api-sports.io\/flags\/es.svg"}},{"player":{"id":916,"name":"M. Diakhaby","photo":"https:\/\/media.api-sports.io\/football\/players\/916.png","type":"Missing Fixture","reason":"Muscle Injury"},"team":{"id":532,"name":"Valencia","logo":"https:\/\/media.api-sports.io\/football\/teams\/532.png"},"fixture":{"id":1391027,"timezone":"UTC","date":"2026-01-24T15:15:00+00:00","timestamp":1769267700},"league":{"id":140,"season":2025,"name":"La Liga","country":"Spain","logo":"https:\/\/media.api-sports.io\/football\/leagues\/140.png","flag":"https:\/\/media.api-sports.io\/flags\/es.svg"}},{"player":{"id":918,"name":"J. Gaya","photo":"https:\/\/media.api-sports.io\/football\/players\/918.png","type":"Missing Fixture","reason":"Yellow Cards"},"team":{"id":532,"name":"Valencia","logo":"https:\/\/media.api-sports.io\/football\/teams\/532.png"},"fixture":{"id":1391027,"timezone":"UTC","date":"2026-01-24T15:15:00+00:00","timestamp":1769267700},"league":{"id":140,"season":2025,"name":"La Liga","country":"Spain","logo":"https:\/\/media.api-sports.io\/football\/leagues\/140.png","flag":"https:\/\/media.api-sports.io\/flags\/es.svg"}},{"player":{"id":913,"name":"C. Rivero","photo":"https:\/\/media.api-sports.io\/football\/players\/913.png","type":"Missing Fixture","reason":"Red Card"},"team":{"id":532,"name":"Valencia","logo":"https:\/\/media.api-sports.io\/football\/teams\/532.png"},"fixture":{"id":1391027,"timezone":"UTC","date":"2026-01-24T15:15:00+00:00","timestamp":1769267700},"league":{"id":140,"season":2025,"name":"La Liga","country":"Spain","logo":"https:\/\/media.api-sports.io\/football\/leagues\/140.png","flag":"https:\/\/media.api-sports.io\/flags\/es.svg"}},{"player":{"id":333672,"name":"C. Tarrega","photo":"https:\/\/media.api-sports.io\/football\/players\/333672.png","type":"Missing Fixture","reason":"Injury"},"team":{"id":532,"name":"Valencia","logo":"https:\/\/media.api-sports.io\/football\/teams\/532.png"},"fixture":{"id":1391027,"timezone":"UTC","date":"2026-01-24T15:15:00+00:00","timestamp":1769267700},"league":{"id":140,"season":2025,"name":"La Liga","country":"Spain","logo":"https:\/\/media.api-sports.io\/football\/leagues\/140.png","flag":"https:\/\/media.api-sports.io\/flags\/es.svg"}},{"player":{"id":286601,"name":"O. El Hilali","photo":"https:\/\/media.api-sports.io\/football\/players\/286601.png","type":"Missing Fixture","reason":"Yellow Cards"},"team":{"id":540,"name":"Espanyol","logo":"https:\/\/media.api-sports.io\/football\/teams\/540.png"},"fixture":{"id":1391027,"timezone":"UTC","date":"2026-01-24T15:15:00+00:00","timestamp":1769267700},"league":{"id":140,"season":2025,"name":"La Liga","country":"Spain","logo":"https:\/\/media.api-sports.io\/football\/leagues\/140.png","flag":"https:\/\/media.api-sports.io\/flags\/es.svg"}},{"player":{"id":47349,"name":"J. Puado","photo":"https:\/\/media.api-sports.io\/football\/players\/47349.png","type":"Missing Fixture","reason":"Injury"},"team":{"id":540,"name":"Espanyol","logo":"https:\/\/media.api-sports.io\/football\/teams\/540.png"},"fixture":{"id":1391027,"timezone":"UTC","date":"2026-01-24T15:15:00+00:00","timestamp":1769267700},"league":{"id":140,"season":2025,"name":"La Liga","country":"Spain","logo":"https:\/\/media.api-sports.io\/football\/leagues\/140.png","flag":"https:\/\/media.api-sports.io\/flags\/es.svg"}}]}